phosphorus/__init__.py
phosphorus/__main__.py
phosphorus/__version__.py
phosphorus/_seven.py
phosphorus/_seven.pyi
phosphorus/construction/__init__.py
phosphorus/construction/api.py
phosphorus/construction/base.py
phosphorus/construction/sdist.py
phosphorus/construction/wheel.py
phosphorus/lib/__init__.py
phosphorus/lib/cli.py
phosphorus/lib/constants.py
phosphorus/lib/contributors.py
phosphorus/lib/exceptions.py
phosphorus/lib/licenses.py
phosphorus/lib/markers.py
phosphorus/lib/metadata.py
phosphorus/lib/packages.py
phosphorus/lib/regex.py
phosphorus/lib/requirements.py
phosphorus/lib/run.py
phosphorus/lib/tags.py
phosphorus/lib/term.py
phosphorus/lib/type_defs.py
phosphorus/lib/utils.py
phosphorus/lib/versions.py
phosphorus/lib/zipped_file.py
phosphorus/py.typed
phosphorus/subcommands/__init__.py
phosphorus/subcommands/base.py
phosphorus/subcommands/build.py
phosphorus-0.2614972128.dist-info/LICENSE.md
phosphorus-0.2614972128.dist-info/METADATA
phosphorus-0.2614972128.dist-info/WHEEL
phosphorus-0.2614972128.dist-info/entry_points.txt
phosphorus-0.2614972128.dist-info/RECORD
