Metadata-Version: 2.3
Name: phosphorus
Version: 0.2614972128
Summary: A PEP 621 compliant build backend
Home-page: https://phosphorus.readthedocs.io/en/stable/
License: BSD-3-Clause
Keywords: build,dependency,packaging
Author: Stephanos Kuma
Author-email: "Stephanos Kuma" <stephanos@kuma.ai>
Requires-Python: >=3.10
Classifier: Development Status :: 3 - Alpha
Classifier: Intended Audience :: Developers
Classifier: License :: OSI Approved :: BSD License
Classifier: Operating System :: OS Independent
Classifier: Programming Language :: Python :: 3 :: Only
Classifier: Topic :: Software Development :: Build Tools
Requires-Dist: tomli (~=2.0) ; python_version < '3.11'
Requires-Dist: trove-classifiers (~=2025.5)
Project-URL: Documentation, https://phosphorus.readthedocs.io/en/stable/
Project-URL: Repository, https://github.com/spapanik/phosphorus
